angrdbg/__init__.py
angrdbg/__main__.py
angrdbg/abstract_debugger.py
angrdbg/back.py
angrdbg/brk.py
angrdbg/context.py
angrdbg/core.py
angrdbg/got_builder.py
angrdbg/idata_builder.py
angrdbg/memory_7.py
angrdbg/memory_8.py
angrdbg/page_7.py
angrdbg/page_8.py
angrdbg/server.py
angrdbg-1.0.16.dist-info/DESCRIPTION.rst
angrdbg-1.0.16.dist-info/METADATA
angrdbg-1.0.16.dist-info/RECORD
angrdbg-1.0.16.dist-info/WHEEL
angrdbg-1.0.16.dist-info/entry_points.txt
angrdbg-1.0.16.dist-info/metadata.json
angrdbg-1.0.16.dist-info/top_level.txt
