Metadata-Version: 2.0
Name: angrdbg
Version: 1.0.16
Summary: Abstract library to generate angr states from a debugger state
Home-page: https://github.com/andreafioraldi/angrdbg
Author: Andrea Fioraldi
Author-email: andreafioraldi@gmail.com
License: BSD 2-Clause
Download-URL: https://github.com/andreafioraldi/angrdbg/archive/1.0.16.tar.gz
Platform: UNKNOWN
Requires-Dist: angr
Requires-Dist: rpyc
Requires-Dist: ipython
